bournemouth_aligner/__init__.py
bournemouth_aligner/cli.py
bournemouth_aligner/core.py
bournemouth_aligner/forced_alignment.py
bournemouth_aligner/utils.py
bournemouth_aligner/cupe2i/model2i.py
bournemouth_aligner/cupe2i/model_utils.py
bournemouth_aligner/cupe2i/windowing.py
bournemouth_aligner/helpers/mel_spec.py
bournemouth_aligner/ipamappers/ph66_mapper.py
bournemouth_aligner/ipamappers/ph66_phonemeizer.py
bournemouth_forced_aligner-0.1.6.dist-info/licenses/LICENSE
bournemouth_forced_aligner-0.1.6.dist-info/METADATA
bournemouth_forced_aligner-0.1.6.dist-info/WHEEL
bournemouth_forced_aligner-0.1.6.dist-info/entry_points.txt
bournemouth_forced_aligner-0.1.6.dist-info/top_level.txt
bournemouth_forced_aligner-0.1.6.dist-info/RECORD
