Metadata-Version: 2.4
Name: bournemouth-forced-aligner
Version: 0.1.6
Summary: Bournemouth Forced Aligner - Phoneme-level timestamp extraction
Home-page: https://github.com/tabahi/bournemouth-forced-aligner
Author: Tabahi
Author-email: Tabahi <tabahi@duck.com>
Maintainer-email: Tabahi <tabahi@duck.com>
License: gplv3
Project-URL: Homepage, https://github.com/tabahi/bournemouth-forced-aligner
Project-URL: Documentation, https://github.com/tabahi/bournemouth-forced-aligner#readme
Project-URL: Repository, https://github.com/tabahi/bournemouth-forced-aligner
Project-URL: Bug Tracker, https://github.com/tabahi/bournemouth-forced-aligner/issues
Project-URL: Changelog, https://github.com/tabahi/bournemouth-forced-aligner/blob/main/CHANGELOG.md
Project-URL: CUPE Models, https://huggingface.co/Tabahi/CUPE-2i
Keywords: phoneme,alignment,speech,audio,timestamp,forced-alignment,bournemouth,CUPE,speech-recognition,linguistics
Classifier: Development Status :: 4 - Beta
Classifier: Intended Audience :: Developers
Classifier: Intended Audience :: Science/Research
Classifier: Intended Audience :: Education
Classifier: License :: OSI Approved :: GNU General Public License v3 (GPLv3)
Classifier: Operating System :: OS Independent
Classifier: Programming Language :: Python :: 3
Classifier: Programming Language :: Python :: 3.8
Classifier: Programming Language :: Python :: 3.9
Classifier: Programming Language :: Python :: 3.10
Classifier: Programming Language :: Python :: 3.11
Classifier: Programming Language :: Python :: 3.12
Classifier: Topic :: Scientific/Engineering :: Artificial Intelligence
Classifier: Topic :: Multimedia :: Sound/Audio :: Analysis
Classifier: Topic :: Scientific/Engineering :: Information Analysis
Classifier: Topic :: Text Processing :: Linguistic
Requires-Python: >=3.8
License-File: LICENSE
Requires-Dist: torch>=1.9.0
Requires-Dist: torchaudio>=0.9.0
Requires-Dist: huggingface_hub>=0.8.0
Requires-Dist: numpy>=1.19.0
Requires-Dist: click>=8.0.0
Requires-Dist: phonemizer>=3.3.0
Requires-Dist: librosa>=0.8.0
Provides-Extra: dev
Requires-Dist: pytest>=6.0; extra == "dev"
Requires-Dist: pytest-cov>=3.0.0; extra == "dev"
Requires-Dist: black>=22.0.0; extra == "dev"
Requires-Dist: flake8>=4.0.0; extra == "dev"
Requires-Dist: mypy>=0.950; extra == "dev"
Requires-Dist: pre-commit>=2.17.0; extra == "dev"
Provides-Extra: test
Requires-Dist: pytest>=6.0; extra == "test"
Requires-Dist: pytest-cov>=3.0.0; extra == "test"
Requires-Dist: pytest-xdist>=2.5.0; extra == "test"
Provides-Extra: docs
Requires-Dist: sphinx>=4.0.0; extra == "docs"
Requires-Dist: sphinx-rtd-theme>=1.0.0; extra == "docs"
Requires-Dist: myst-parser>=0.17.0; extra == "docs"
Provides-Extra: audio
Requires-Dist: librosa>=0.8.0; extra == "audio"
Requires-Dist: soundfile>=0.10.0; extra == "audio"
Requires-Dist: pydub>=0.25.0; extra == "audio"
Provides-Extra: all
Requires-Dist: bournemouth-forced-aligner[audio,dev,docs,test]; extra == "all"
Dynamic: author
Dynamic: home-page
Dynamic: license-file
Dynamic: requires-python
